noshot/__init__.py
noshot/ftp_server.py
noshot/main.py
noshot/todo.py
noshot/data/DLE FSD BDA LC.zip
noshot/data/ftp/DLE FSD BDA/LC.iso
noshot/data/ftp/DLE FSD BDA/LC/Doc/126014056.odt
noshot/data/ftp/DLE FSD BDA/LC/Nice/GENERAL ORACLE APEX EXAM TEMPLATE.txt
noshot/data/ftp/DLE FSD BDA/LC/Nice/eco_toys_exam.sql
noshot/data/ftp/DLE FSD BDA/LC/Nice/general_commands.txt
noshot/data/ftp/DLE FSD BDA/LC/Nice/nice_loc.txt
noshot/data/ftp/DLE FSD BDA/LC/Nice/sqlcommands.txt
noshot/data/ftp/DLE FSD BDA/LC/Old/Book_World-main.zip
noshot/data/ftp/DLE FSD BDA/LC/Old/brookstrut-sample-app.zip
noshot/data/ftp/DLE FSD BDA/LC/Old/classMonitoring.zip
noshot/data/ftp/DLE FSD BDA/LC/Old/customers.zip
noshot/data/ftp/DLE FSD BDA/LC/Old/f195927.sql
noshot/data/ftp/DLE FSD BDA/LC/Old/f234546.zip
noshot/data/ftp/DLE FSD BDA/LC/Old/f284000.sql
noshot/data/ftp/DLE FSD BDA/LC/Old/f37118.sql
noshot/data/ftp/DLE FSD BDA/LC/Old/opportunities.zip
noshot/data/ftp/DLE FSD BDA/LC/Old/store.zip
noshot/data/ftp/DLE FSD BDA/LC/Super/LOW CODE.txt
noshot/data/ftp/DLE FSD BDA/LC/Super/model.sql
noshot/data/others/find_server.py
noshot/data/storage/assets/icon.ico
noshot/data/storage/assets/distributions/empty.txt
noshot/data/storage/assets/distributions/noshot-37.0.0-py3-none-any.whl
noshot/data/storage/assets/offline/offline_requirements.txt
noshot/data/storage/assets/offline/offline_bundle/certifi-2025.10.5-py3-none-any.whl
noshot/data/storage/assets/offline/offline_bundle/charset_normalizer-3.4.4-cp310-cp310-win_amd64.whl
noshot/data/storage/assets/offline/offline_bundle/charset_normalizer-3.4.4-cp311-cp311-win_amd64.whl
noshot/data/storage/assets/offline/offline_bundle/charset_normalizer-3.4.4-cp312-cp312-win_amd64.whl
noshot/data/storage/assets/offline/offline_bundle/charset_normalizer-3.4.4-cp313-cp313-win_amd64.whl
noshot/data/storage/assets/offline/offline_bundle/charset_normalizer-3.4.4-cp39-cp39-win_amd64.whl
noshot-37.0.0.dist-info/licenses/LICENSE.txt
noshot-37.0.0.dist-info/METADATA
noshot-37.0.0.dist-info/WHEEL
noshot-37.0.0.dist-info/entry_points.txt
noshot-37.0.0.dist-info/top_level.txt
noshot-37.0.0.dist-info/RECORD
